.config.yaml
CHANGELOG.md
data/H37RV_genome/compass-mask.bed
data/H37RV_genome/h37rv.fa.gz
data/H37RV_genome/h37rv.fa.gz.fai
data/H37RV_genome/h37rv.fa.gz.gzi
data/decontamination_db/remove_contam.tsv.gz
external_scripts/apply_filters.py
external_scripts/consensus.py
external_scripts/filter_contamination.py
tbpore/__init__.py
tbpore/__main__.py
tbpore/cli.py
tbpore/clustering.py
tbpore/constants.py
tbpore/external_tools.py
tbpore/tbpore.py
tbpore/utils.py
tbpore-0.7.1.dist-info/LICENSE
tbpore-0.7.1.dist-info/METADATA
tbpore-0.7.1.dist-info/WHEEL
tbpore-0.7.1.dist-info/entry_points.txt
tbpore-0.7.1.dist-info/RECORD
