Metadata-Version: 2.1
Name: tbpore
Version: 0.7.1
Summary: Mycobacterium tuberculosis genomic analysis from Nanopore sequencing data
Home-page: https://github.com/mbhall88/tbpore
License: MIT
Keywords: tuberculosis,nanopore,diagnostics,genomics,variant-calling,resistance-prediction
Author: Michael Hall
Author-email: michael@mbh.sh
Requires-Python: >=3.8,<4.0
Classifier: License :: OSI Approved :: MIT License
Classifier: Programming Language :: Python :: 3
Classifier: Programming Language :: Python :: 3.8
Classifier: Programming Language :: Python :: 3.9
Classifier: Programming Language :: Python :: 3.10
Classifier: Programming Language :: Python :: 3.11
Requires-Dist: click (>=8.0.3,<9.0.0)
Requires-Dist: cyvcf2 (>=0.30,<0.31)
Requires-Dist: loguru (>=0.5.3,<0.6.0)
Requires-Dist: networkx (>=2.8,<3.0)
Requires-Dist: pandas (>=1.4.2,<2.0.0)
Requires-Dist: pysam (<1.0)
Requires-Dist: pyyaml (>=6.0)
Project-URL: Repository, https://github.com/mbhall88/tbpore
